README.rst
setup.py
hue/__init__.py
hue/hue.py
python_hue.egg-info/PKG-INFO
python_hue.egg-info/SOURCES.txt
python_hue.egg-info/dependency_links.txt
python_hue.egg-info/pbr.json
python_hue.egg-info/requires.txt
python_hue.egg-info/top_level.txt